pupyC3D/__init__.py
pupyC3D/c3dfile.py
pupyC3D/decoder.py
pupyc3d-0.1.3.dist-info/licenses/LICENSE
pupyc3d-0.1.3.dist-info/METADATA
pupyc3d-0.1.3.dist-info/WHEEL
pupyc3d-0.1.3.dist-info/top_level.txt
pupyc3d-0.1.3.dist-info/RECORD
