Metadata-Version: 2.4
Name: pupyC3D
Version: 0.1.3
Summary: Pure Python C3D reader and writer for biomechanics and motion capture data
Home-page: https://github.com/Norton-breman/pupyC3D
Author: Antoine MARIN
Author-email: Antoine MARIN <antoine.marin@univ-rennes2.fr>
Maintainer-email: Antoine MARIN <antoine.marin@univ-rennes2.fr>
License: CC-BY-NC-4.0
Project-URL: Homepage, https://github.com/Norton-breman/pupyC3D
Project-URL: Repository, https://github.com/Norton-breman/pupyC3D
Project-URL: Bug Reports, https://github.com/Norton-breman/pupyC3D/issues
Keywords: c3d,biomechanics,motion-capture,3d-coordinates
Classifier: Development Status :: 4 - Beta
Classifier: Intended Audience :: Science/Research
Classifier: Topic :: Scientific/Engineering :: Bio-Informatics
Classifier: Topic :: Scientific/Engineering :: Human Machine Interfaces
Classifier: License :: OSI Approved :: MIT License
Classifier: Programming Language :: Python :: 3
Classifier: Programming Language :: Python :: 3.6
Classifier: Programming Language :: Python :: 3.7
Classifier: Programming Language :: Python :: 3.8
Classifier: Programming Language :: Python :: 3.9
Classifier: Programming Language :: Python :: 3.10
Classifier: Programming Language :: Python :: 3.11
Classifier: Operating System :: OS Independent
Requires-Python: >=3.6
License-File: LICENSE
Requires-Dist: numpy>=1.16.0
Dynamic: author
Dynamic: home-page
Dynamic: license-file
Dynamic: requires-python
